insanic/__init__.py
insanic/adapters.py
insanic/app.py
insanic/choices.py
insanic/connections.py
insanic/decorators.py
insanic/errors.py
insanic/exceptions.py
insanic/functional.py
insanic/handlers.py
insanic/listeners.py
insanic/loading.py
insanic/metrics.py
insanic/middleware.py
insanic/models.py
insanic/monitor.py
insanic/permissions.py
insanic/protocol.py
insanic/request.py
insanic/router.py
insanic/scopes.py
insanic/status.py
insanic/throttles.py
insanic/views.py
insanic/authentication/__init__.py
insanic/authentication/handlers.py
insanic/conf/__init__.py
insanic/conf/config.py
insanic/conf/global_settings.py
insanic/log/__init__.py
insanic/log/formatters.py
insanic/services/__init__.py
insanic/services/adapters.py
insanic/services/client.py
insanic/services/registry.py
insanic/services/utils.py
insanic/utils/__init__.py
insanic/utils/datetime.py
insanic_framework-0.9.2.dist-info/LICENSE
insanic_framework-0.9.2.dist-info/METADATA
insanic_framework-0.9.2.dist-info/WHEEL
insanic_framework-0.9.2.dist-info/top_level.txt
insanic_framework-0.9.2.dist-info/RECORD
