Metadata-Version: 2.1
Name: insanic-framework
Version: 0.9.2
Summary: An API framework that extends sanic with a focus on microservices.
Home-page: https://github.com/crazytruth/insanic
Author: Kwang Jin Kim
Author-email: kwangjinkim@gmail.com
License: MIT
Project-URL: Documentation, https://insanic.readthedocs.io/en/latest/
Project-URL: Source, https://github.com/crazytruth/insanic
Project-URL: Tracker, https://github.com/crazytruth/insanic/issues
Keywords: api framework sanic async asyncio microservice msa python python3
Platform: UNKNOWN
Classifier: Intended Audience :: Developers
Classifier: Development Status :: 3 - Alpha
Classifier: License :: OSI Approved :: MIT License
Classifier: Programming Language :: Python :: 3.6
Classifier: Programming Language :: Python :: 3.7
Classifier: Programming Language :: Python :: 3.8
Classifier: Topic :: Software Development :: Libraries :: Application Frameworks
Requires-Python: >=3.6
Requires-Dist: uvloop
Requires-Dist: sanic (<20.10,>=20.03)
Requires-Dist: aioredis (>=1.1.0)
Requires-Dist: PyJWT
Requires-Dist: aiotask-context
Requires-Dist: python-dateutil
Requires-Dist: prometheus-client (==0.5.0)
Requires-Dist: psutil
Requires-Dist: packaging
